{
  "minecraft:recipes/tools/fishing_rod": {
    "criteria": {
      "has_string": "2023-05-27 22:16:47 -0400"
    },
    "done": true
  },
  "minecraft:recipes/decorations/candle": {
    "criteria": {
      "has_string": "2023-05-27 22:16:47 -0400"
    },
    "done": true
  },
  "minecraft:recipes/decorations/snow": {
    "criteria": {
      "has_snowball": "2023-05-27 22:16:51 -0400"
    },
    "done": true
  },
  "minecraft:recipes/combat/bow": {
    "criteria": {
      "has_string": "2023-05-27 22:16:47 -0400"
    },
    "done": true
  },
  "minecraft:recipes/combat/crossbow": {
    "criteria": {
      "has_string": "2023-05-27 22:16:47 -0400"
    },
    "done": true
  },
  "minecraft:recipes/decorations/loom": {
    "criteria": {
      "has_string": "2023-05-27 22:16:47 -0400"
    },
    "done": true
  },
  "minecraft:recipes/building_blocks/white_wool_from_string": {
    "criteria": {
      "has_string": "2023-05-27 22:16:47 -0400"
    },
    "done": true
  },
  "minecraft:recipes/redstone/tripwire_hook": {
    "criteria": {
      "has_string": "2023-05-27 22:16:47 -0400"
    },
    "done": true
  },
  "minecraft:recipes/building_blocks/snow_block": {
    "criteria": {
      "has_snowball": "2023-05-27 22:16:51 -0400"
    },
    "done": true
  },
  "minecraft:adventure/adventuring_time": {
    "criteria": {
      "minecraft:old_growth_pine_taiga": "2023-05-27 22:16:30 -0400",
      "minecraft:river": "2023-05-27 22:19:30 -0400",
      "minecraft:lush_caves": "2023-05-27 22:20:47 -0400",
      "minecraft:old_growth_spruce_taiga": "2023-05-27 22:19:31 -0400"
    },
    "done": false
  },
  "minecraft:story/root": {
    "criteria": {
      "crafting_table": "2023-05-27 22:16:56 -0400"
    },
    "done": true
  },
  "DataVersion": 2975
}